resources/portal/docs.json
resources/portal/icon.svg
resources/portal/main.js
resources/portal/manifest.edn
resources/portal/ws.js
portal/__init__.py
portal/api.cljc
portal/async.cljc
portal/client/clr.clj
portal/client/common.cljs
portal/client/dart.cljd
portal/client/jvm.clj
portal/client/node.cljs
portal/client/planck.cljs
portal/client/py.lpy
portal/client/web.cljs
portal/client.cljc
portal/colors.cljc
portal/console.cljc
portal/extensions/electron.cljs
portal/extensions/pwa.cljs
portal/extensions/vs_code.cljs
portal/extensions/vs_code_notebook.cljs
portal/main.clj
portal/main.cljs
portal/nrepl.clj
portal/nrepl.cljr
portal/resources.cljc
portal/runtime/browser.cljc
portal/runtime/clr/assembly.clj
portal/runtime/clr/client.clj
portal/runtime/clr/launcher.clj
portal/runtime/clr/server.clj
portal/runtime/cson.cljc
portal/runtime/datafy.cljc
portal/runtime/edn.cljc
portal/runtime/fs.cljc
portal/runtime/index.cljc
portal/runtime/json.cljc
portal/runtime/json_buffer.cljc
portal/runtime/jvm/client.clj
portal/runtime/jvm/commands.clj
portal/runtime/jvm/editor.clj
portal/runtime/jvm/launcher.clj
portal/runtime/jvm/server.clj
portal/runtime/launcher.cljc
portal/runtime/macros.cljc
portal/runtime/node/client.cljs
portal/runtime/node/launcher.cljs
portal/runtime/node/server.cljs
portal/runtime/npm.cljc
portal/runtime/protocols.cljc
portal/runtime/python/client.lpy
portal/runtime/python/launcher.lpy
portal/runtime/python/server.lpy
portal/runtime/rpc.cljc
portal/runtime/shell.cljc
portal/runtime/transit.cljc
portal/runtime/web/client.cljs
portal/runtime/web/launcher.cljs
portal/runtime.cljc
portal/shadow/preload.cljs
portal/shadow/remote.clj
portal/shadow/remote.cljs
portal/shortcuts.cljs
portal/spec.cljc
portal/sync.cljc
portal/ui/api.cljs
portal/ui/app.cljs
portal/ui/cljs.cljs
portal/ui/commands.cljs
portal/ui/connection_status.cljs
portal/ui/core.cljs
portal/ui/drag_and_drop.cljs
portal/ui/embed.cljs
portal/ui/filter.cljc
portal/ui/html.cljs
portal/ui/icons.cljs
djblue_portal-0.62.2.dist-info/LICENSE
djblue_portal-0.62.2.dist-info/METADATA
djblue_portal-0.62.2.dist-info/WHEEL
djblue_portal-0.62.2.dist-info/RECORD
