Metadata-Version: 2.3
Name: djblue.portal
Version: 0.62.2
Summary: A clojure tool to navigate through your data.
License: MIT License
Keywords: clojure,basilisp,inspector,portal,datafy,nav
Author: djblue
Author-email: djblue@users.noreply.github.com
Requires-Python: >= 3.8
Classifier: License :: Other/Proprietary License
Classifier: Programming Language :: Python :: 3
Classifier: Programming Language :: Python :: 3.8
Classifier: Programming Language :: Python :: 3.9
Classifier: Programming Language :: Python :: 3.10
Classifier: Programming Language :: Python :: 3.11
Classifier: Programming Language :: Python :: 3.12
Classifier: Programming Language :: Python :: 3.13
Requires-Dist: aiohttp (>=3.11.11)
Requires-Dist: asyncio (>=3.4.3)
Requires-Dist: basilisp (>=0.4.0)
Project-URL: Changelog, https://github.com/djblue/portal/blob/master/CHANGELOG.md
Project-URL: Documentation, https://cljdoc.org/d/djblue/portal/
Project-URL: Homepage, https://github.com/djblue/portal
Project-URL: Issues, https://github.com/djblue/portal/issues
Project-URL: Standalone, https://djblue.github.io/portal/
